MANIFEST.in
setup.py
django_weather_darksky/__init__.py
django_weather_darksky/admin.py
django_weather_darksky/api.py
django_weather_darksky/apps.py
django_weather_darksky/helpers.py
django_weather_darksky/models.py
django_weather_darksky/settings.py
django_weather_darksky.egg-info/PKG-INFO
django_weather_darksky.egg-info/SOURCES.txt
django_weather_darksky.egg-info/dependency_links.txt
django_weather_darksky.egg-info/not-zip-safe
django_weather_darksky.egg-info/requires.txt
django_weather_darksky.egg-info/top_level.txt
django_weather_darksky/locale/ru/LC_MESSAGES/django.mo
django_weather_darksky/locale/ru/LC_MESSAGES/django.po
django_weather_darksky/management/__init__.py
django_weather_darksky/management/__pycache__/__init__.cpython-35.pyc
django_weather_darksky/management/commands/__init__.py
django_weather_darksky/management/commands/load_forecast.py
django_weather_darksky/management/commands/__pycache__/__init__.cpython-35.pyc
django_weather_darksky/management/commands/__pycache__/load_forecast.cpython-35.pyc
django_weather_darksky/migrations/0001_initial.py
django_weather_darksky/migrations/0002_weatherlocation_slug.py
django_weather_darksky/migrations/0003_auto_20170321_1448.py
django_weather_darksky/migrations/__init__.py
django_weather_darksky/migrations/__pycache__/0001_initial.cpython-35.pyc
django_weather_darksky/migrations/__pycache__/0002_weatherlocation_slug.cpython-35.pyc
django_weather_darksky/migrations/__pycache__/0003_auto_20170321_1448.cpython-35.pyc
django_weather_darksky/migrations/__pycache__/__init__.cpython-35.pyc
django_weather_darksky/templates/django_weather_darksky/informer.html
django_weather_darksky/templatetags/__init__.py
django_weather_darksky/templatetags/django_weather_darksky.py
django_weather_darksky/templatetags/__pycache__/__init__.cpython-35.pyc
django_weather_darksky/templatetags/__pycache__/django_weather_darksky.cpython-35.pyc