Metadata-Version: 1.1
Name: django-weather-darksky
Version: 0.1.2
Summary: Wrapper for darksky.net API for django
Home-page: https://github.com/slavama/django_weather_darksky
Author: Slava M
Author-email: master@neucom.ru
License: MIT License
Keywords: forecast forecast.io darksky.net weather
Platform: UNKNOWN
Classifier: Development Status :: 3 - Alpha
Classifier: Environment :: Web Environment
Classifier: Framework :: Django
Classifier: Intended Audience :: Developers
Classifier: Intended Audience :: Developers
Classifier: Natural Language :: English
Classifier: Programming Language :: Python :: 2
Classifier: Programming Language :: Python :: 2.7
Classifier: Programming Language :: Python :: 3
Classifier: Programming Language :: Python :: 3.5
Requires: python (>= 2.7)
Requires: django (>= 1.8)
